cirs_063/CIRS_063.py
cirs_063/Phantom_analysis_toolbox.py
cirs_063/__init__.py
cirs_063/constants.py
cirs_063/main_CIRS_063.py
cirs_063/main_CIRS_063_WAD.py
ctpa_cirs063-0.1.1.1.dist-info/LICENSE
ctpa_cirs063-0.1.1.1.dist-info/METADATA
ctpa_cirs063-0.1.1.1.dist-info/WHEEL
ctpa_cirs063-0.1.1.1.dist-info/top_level.txt
ctpa_cirs063-0.1.1.1.dist-info/RECORD
